Metadata-Version: 2.1
Name: m2-template-fill
Version: 0.0.1
Summary: Tools for using Jinja as an application.
Author: March
Author-email: m2.march@gmail.com
License: MIT
Platform: UNKNOWN
Requires-Python: >=3.6
License-File: LICENSE
